__init__.py
sdk.py
sdk_api_package-0.0.1.dist-info/LICENSE
sdk_api_package-0.0.1.dist-info/METADATA
sdk_api_package-0.0.1.dist-info/WHEEL
sdk_api_package-0.0.1.dist-info/top_level.txt
sdk_api_package-0.0.1.dist-info/RECORD
