Metadata-Version: 2.1
Name: sdk-api-package
Version: 0.0.1
Summary: PythonSDK for Blockhouse
Author-email: Omar Abdelmotaleb <omarahmed925@gmail.com>
Classifier: Programming Language :: Python :: 3
Classifier: License :: OSI Approved :: MIT License
Classifier: Operating System :: OS Independent
Requires-Python: >=3.8
License-File: LICENSE
